alexandria/__init__.py
alexandria/celery.py
alexandria/core/__init__.py
alexandria/core/api.py
alexandria/core/apps.py
alexandria/core/factories.py
alexandria/core/filters.py
alexandria/core/locale/de/LC_MESSAGES/django.mo
alexandria/core/locale/de/LC_MESSAGES/django.po
alexandria/core/locale/en/LC_MESSAGES/django.mo
alexandria/core/locale/en/LC_MESSAGES/django.po
alexandria/core/locale/it/LC_MESSAGES/django.mo
alexandria/core/locale/it/LC_MESSAGES/django.po
alexandria/core/management/commands/__init__.py
alexandria/core/management/commands/encrypt_files.py
alexandria/core/management/commands/fix_copied_file_references.py
alexandria/core/management/commands/generate_content_vectors.py
alexandria/core/management/commands/generate_missing_checksums.py
alexandria/core/management/commands/generate_missing_thumbnails.py
alexandria/core/management/commands/migrate_document_title_and_description.py
alexandria/core/management/commands/search.py
alexandria/core/management/commands/set_mime_type_and_size.py
alexandria/core/migrations/0001_initial.py
alexandria/core/migrations/0002_tags_monolingual.py
alexandria/core/migrations/0003_file_upload_status.py
alexandria/core/migrations/0004_tag_synonym_group.py
alexandria/core/migrations/0005_rename_type_and_meta.py
alexandria/core/migrations/0006_rename_metainfo_jsonfield_verbose_name.py
alexandria/core/migrations/0007_category_parent.py
alexandria/core/migrations/0008_document_date.py
alexandria/core/migrations/0009_file_checksum.py
alexandria/core/migrations/0010_mark.py
alexandria/core/migrations/0011_tag_uuid.py
alexandria/core/migrations/0012_tag_uuid_schema.py
alexandria/core/migrations/0013_file_content.py
alexandria/core/migrations/0014_file_mime_type_size.py
alexandria/core/migrations/0015_fix_modified_by_description.py
alexandria/core/migrations/0016_category_allowed_mime_types.py
alexandria/core/migrations/0017_file_vector.py
alexandria/core/migrations/0018_alter_document_description_alter_document_title.py
caluma_alexandria-8.5.0.dist-info/METADATA
caluma_alexandria-8.5.0.dist-info/WHEEL
caluma_alexandria-8.5.0.dist-info/licenses/LICENSE
caluma_alexandria-8.5.0.dist-info/RECORD
