Metadata-Version: 2.4
Name: caluma-alexandria
Version: 8.5.0
Summary: Document management service
License: GPL-3.0-or-later
License-File: LICENSE
Author: Caluma
Author-email: info@caluma.io
Requires-Python: >=3.12,<4.0
Classifier: Development Status :: 4 - Beta
Classifier: Intended Audience :: Developers
Classifier: License :: OSI Approved :: GNU General Public License v3 or later (GPLv3+)
Classifier: Programming Language :: Python :: 3
Classifier: Programming Language :: Python :: 3.12
Classifier: Programming Language :: Python :: 3.13
Classifier: Programming Language :: Python :: 3.14
Requires-Dist: boto3 (>=1.34.157,<2.0.0)
Requires-Dist: celery (>=5.4.0,<6.0.0)
Requires-Dist: clamdpy (>=0.1.0.post1,<0.2.0)
Requires-Dist: django (>=4.2,<5.3)
Requires-Dist: django-environ (>=0.9.0,<0.13.0)
Requires-Dist: django-filter (>=22.1,<26.0)
Requires-Dist: django-generic-api-permissions (>=1.0.0,<4)
Requires-Dist: django-localized-fields (>=6.8b5,<7.0)
Requires-Dist: django-presigned-url (>=0.1.1,<0.2.0)
Requires-Dist: django-storages[s3] (>=1.14.2,<2.0.0)
Requires-Dist: djangorestframework (>=3.13.0,<4.0.0)
Requires-Dist: djangorestframework-jsonapi (>=5.0.0,<9.0.0)
Requires-Dist: gunicorn (>=23.0.0,<24.0.0)
Requires-Dist: manabi (>=1.4.0,<3)
Requires-Dist: mozilla-django-oidc (>=2,<5)
Requires-Dist: pghstore (>=2.0.2,<3.0.0)
Requires-Dist: preview-generator (>=0.29,<0.30)
Requires-Dist: psutil (>=5.9.8,<8.0.0)
Requires-Dist: psycopg (>=3.2.1,<4.0.0)
Requires-Dist: python-magic (>=0.4.27,<0.5.0)
Requires-Dist: redis (>=5.0.8,<7.0.0)
Requires-Dist: requests (>=2.31.0,<3.0.0)
Requires-Dist: tika (>=2.6,<4.0)
Requires-Dist: tqdm (>=4.66.5,<5.0.0)
Project-URL: Repository, https://github.com/projectcaluma/alexandria
